py2vhdl_ai/__init__.py
py2vhdl_ai/example.py
py2vhdl_ai-0.0.1.dist-info/LICENSE
py2vhdl_ai-0.0.1.dist-info/METADATA
py2vhdl_ai-0.0.1.dist-info/WHEEL
py2vhdl_ai-0.0.1.dist-info/top_level.txt
py2vhdl_ai-0.0.1.dist-info/RECORD
