Metadata-Version: 2.1
Name: py2vhdl_ai
Version: 0.0.1
Summary: Test build
Author-email: Yevhenii Holopotyliuk <yevhenii.holopotyliuk@gmail.com>
Project-URL: Homepage, https://github.com/YevheniiHolopotyliuk/Py2VHDL-AI
Project-URL: Issues, https://github.com/YevheniiHolopotyliuk/Py2VHDL-AI
Classifier: Programming Language :: Python :: 3
Classifier: License :: OSI Approved :: MIT License
Classifier: Operating System :: OS Independent
Requires-Python: >=3.0
License-File: LICENSE
